injectify/__init__.py
injectify/__version__.py
injectify/api.py
injectify/exceptions.py
injectify/injectors.py
injectify/inspect_mate.py
injectify/structures.py
injectify/utils.py
injectify-0.2.0.dist-info/LICENSE
injectify-0.2.0.dist-info/METADATA
injectify-0.2.0.dist-info/WHEEL
injectify-0.2.0.dist-info/top_level.txt
injectify-0.2.0.dist-info/RECORD
