Metadata-Version: 2.1
Name: injectify
Version: 0.2.0
Summary: Python Code Injection Library
Home-page: https://github.com/Maltzur/injectify
Author: Mitchell Marsden
Author-email: email@mitchellmarsden.com
License: BSD
Platform: UNKNOWN
Classifier: Development Status :: 4 - Beta
Classifier: Intended Audience :: Developers
Classifier: Natural Language :: English
Classifier: License :: OSI Approved :: BSD License
Classifier: Programming Language :: Python :: 3 :: Only
Classifier: Programming Language :: Python :: 3
Classifier: Programming Language :: Python :: 3.5
Classifier: Programming Language :: Python :: 3.6
Classifier: Programming Language :: Python :: 3.7
Classifier: Programming Language :: Python :: 3.8
Classifier: Topic :: Software Development :: Code Generators
Requires-Python: >=3.5
Requires-Dist: astunparse (>=1.1.0)
